fastapi_offline_docs/__init__.py
fastapi_offline_docs/py.typed
fastapi_offline_docs/static/redoc.standalone.js
fastapi_offline_docs/static/swagger-ui-bundle.js
fastapi_offline_docs/static/swagger-ui.css
fastapi_offline_docs-1.1.0.dist-info/METADATA
fastapi_offline_docs-1.1.0.dist-info/WHEEL
fastapi_offline_docs-1.1.0.dist-info/RECORD
