Metadata-Version: 2.4
Name: fastapi-offline-docs
Version: 1.1.0
Summary: Offline API docs for FastAPI
Author: community-of-python
Requires-Python: <4,>=3.9
Requires-Dist: fastapi<1.0.0,>=0.101.1
